[
  {
    "titel": "Personal Reminiscences of India",
    "autor": "Rev. William Butler D.D.",
    "sprache": "Englisch",
    "schlagwörter": ["Indien", "Personal", "Reminiscences"]
  },
  {
    "titel": "Seven Years in Ceylon: Stories of Missionary Life",
    "autor": "Mary and Margaret W. Leitch",
    "sprache": "Englisch",
    "schlagwörter": ["Sri Lanka/Ceylon", "Ceylon", "Stories", "Missionary"]
  },
  {
    "titel": "Die Engländer in Indien, Dritter Band",
    "autor": "Johann Wilhelm von Archenholz",
    "sprache": "Deutsch",
    "schlagwörter": ["Engländer", "Indien", "Dritter"]
  },
  {
    "titel": "Aufsätze",
    "autor": "Marie Estermann",
    "sprache": "Deutsch",
    "schlagwörter": ["Aufsätze"]
  },
  {
    "titel": "The Indian Empire at War",
    "autor": "George Morton-Jack",
    "sprache": "Englisch",
    "schlagwörter": ["Indien", "Indian", "Empire"]
  },
  {
    "titel": "Armies of the East India Company 1750-1850",
    "autor": "Stuart Reid",
    "sprache": "Englisch",
    "schlagwörter": ["Indien", "Waffen", "Militärgeschichte", "Armies", "Company"]
  },
  {
    "titel": "Medieval Indian Armies (2): Indo-Islamic Forces 7th-Early 16th Centuries",
    "autor": "David Nicolle",
    "sprache": "Englisch",
    "schlagwörter": ["Indien", "Waffen", "Militärgeschichte", "Medieval", "Indian", "Armies"]
  },
  {
    "titel": "Bengal Cavalry Regiments 1857-1914",
    "autor": "Ronald Harris",
    "sprache": "Englisch",
    "schlagwörter": ["1857", "Sepoy-Aufstand", "Bengal", "Cavalry", "Regiments"]
  },
  {
    "titel": "Imphal 1944: The Japanese Invasion of India",
    "autor": "Hemant Singh Katoch, Illustrated by Peter Dennis",
    "sprache": "Englisch",
    "schlagwörter": ["Indien", "Imphal (1944)", "Imphal", "Japanese", "Invasion"]
  },
  {
    "titel": "Plassey 1757: Clive of India's Finest Hour",
    "autor": "Peter Harrington",
    "sprache": "Englisch",
    "schlagwörter": ["Indien", "Plassey (1757)", "Plassey", "India's", "Finest"]
  },
  {
    "titel": "Adventurers: The Improbable Rise of the East India Company",
    "autor": "David Howarth",
    "sprache": "Englisch",
    "schlagwörter": ["Indien", "Adventurers", "Improbable", "Company"]
  },
  {
    "titel": "Cruel Kings and Mean Queens",
    "autor": "Terry Deary",
    "sprache": "Englisch",
    "schlagwörter": ["Queens"]
  },
  {
    "titel": "A History of Ancient and Early Medieval India - Second Edition",
    "autor": "Upinder Singh",
    "sprache": "Englisch",
    "schlagwörter": ["Indien", "Geschichte", "History", "Ancient", "Medieval", "Second"]
  },
  {
    "titel": "The Royal Rajputs",
    "autor": "Maharao Brij Raj Singh of Kotah",
    "sprache": "Englisch",
    "schlagwörter": ["Rajput", "Rajputs"]
  },
  {
    "titel": "The Anglo-Indians: A Portrait of a Community",
    "autor": "Barry O'Brien",
    "sprache": "Englisch",
    "schlagwörter": ["Indien", "Indians", "Portrait", "Community"]
  },
  {
    "titel": "Once There Was a City Named Dilli",
    "autor": "Intizar Husain",
    "sprache": "Englisch",
    "schlagwörter": []
  },
  {
    "titel": "Muslims in Indian Cities",
    "autor": "Laurent Gayer and Christophe Jaffrelot",
    "sprache": "Englisch",
    "schlagwörter": ["Indien", "Muslims", "Indian", "Cities"]
  },
  {
    "titel": "The Ancient Geography of India",
    "autor": "Alexander Cunningham",
    "sprache": "Englisch",
    "schlagwörter": ["Indien", "Ancient", "Geography"]
  },
  {
    "titel": "Invisible City: The Hidden Monuments of Delhi",
    "autor": "Rakhshanda Jalil",
    "sprache": "Englisch",
    "schlagwörter": ["Delhi", "Invisible", "Hidden", "Monuments"]
  },
  {
    "titel": "Hitler and India",
    "autor": "Vaibhav Purandare",
    "sprache": "Englisch",
    "schlagwörter": ["Indien", "Hitler"]
  },
  {
    "titel": "The Forgotten Cities of Delhi",
    "autor": "Rana Safvi",
    "sprache": "Englisch",
    "schlagwörter": ["Delhi", "Forgotten", "Cities"]
  },
  {
    "titel": "Shahjahanabad: The Living City of Old Delhi",
    "autor": "William Dalrymple",
    "sprache": "Englisch",
    "schlagwörter": ["Delhi", "Shahjahanabad", "Living"]
  },
  {
    "titel": "Kings and Queens of India: Famous Rulers and Dynasties That Shaped the Country",
    "autor": "Anu Kumar",
    "sprache": "Englisch",
    "schlagwörter": ["Indien", "Queens", "Famous", "Rulers", "Dynasties", "Shaped"]
  },
  {
    "titel": "Der Hinduismus",
    "autor": "Heinrich von Stietencron",
    "sprache": "Deutsch",
    "schlagwörter": ["Hinduismus"]
  },
  {
    "titel": "Which of Us Are Aryans",
    "autor": "Romila Thapar, Michael Witzel, Jaya Menon, Kai Friese, Razib Khan",
    "sprache": "Englisch",
    "schlagwörter": ["Aryans"]
  },
  {
    "titel": "Forgotten Delhi: From a Heritage Walker's Diary",
    "autor": "R. S. Sethi",
    "sprache": "Englisch",
    "schlagwörter": ["Delhi", "Forgotten", "Heritage", "Walker's"]
  },
  {
    "titel": "1553: Mary I",
    "autor": "John Edwards",
    "sprache": "Englisch",
    "schlagwörter": []
  },
  {
    "titel": "1558: Elizabeth I",
    "autor": "Helen Castor",
    "sprache": "Englisch",
    "schlagwörter": ["Elizabeth"]
  },
  {
    "titel": "Thomas Cromwell: The Rise and Fall of Henry VIII's Most Notorious Minister",
    "autor": "Robert Hutchinson",
    "sprache": "Englisch",
    "schlagwörter": ["Thomas", "Cromwell", "Notorious", "Minister"]
  },
  {
    "titel": "The Armour and Arms of Henry VIII",
    "autor": "Thomas Richardson",
    "sprache": "Englisch",
    "schlagwörter": ["Waffen", "Rüstung", "Armour"]
  },
  {
    "titel": "Fort Nelson",
    "autor": "Souvenir Guide",
    "sprache": "Englisch",
    "schlagwörter": ["Reiseführer", "Nelson"]
  },
  {
    "titel": "Islamic Arms and Armour",
    "autor": "Thom Richardson",
    "sprache": "Englisch",
    "schlagwörter": ["Waffen", "Rüstung", "Islamic", "Armour"]
  },
  {
    "titel": "Indian Arms and Armour",
    "autor": "Thom Richardson and Natascha Bennet",
    "sprache": "Englisch",
    "schlagwörter": ["Indien", "Waffen", "Rüstung", "Indian", "Armour"]
  },
  {
    "titel": "Henry VIII in 100 Objects",
    "autor": "Paul Kendall",
    "sprache": "Englisch",
    "schlagwörter": ["Objects"]
  },
  {
    "titel": "Stonehenge",
    "autor": "Stonehenge",
    "sprache": "Englisch",
    "schlagwörter": []
  },
  {
    "titel": "Europe Between the Oceans: 9000 BC-AD 1000",
    "autor": "Barry Cunliffe",
    "sprache": "Englisch",
    "schlagwörter": ["Europe", "Between", "Oceans"]
  },
  {
    "titel": "Masters of War",
    "autor": "DK",
    "sprache": "Englisch",
    "schlagwörter": ["Masters"]
  },
  {
    "titel": "Don Quixote",
    "autor": "Miguel de Cervantes",
    "sprache": "Englisch",
    "schlagwörter": ["Quixote"]
  },
  {
    "titel": "Procès de Sorcellerie dans la Vallée de Choches 1466-1467",
    "autor": "Chantal Amman-Doubliez",
    "sprache": "Französisch",
    "schlagwörter": ["Sorcellerie", "Choches"]
  },
  {
    "titel": "Torture Instruments",
    "autor": "Exhibition Guide",
    "sprache": "Englisch und Spanisch",
    "schlagwörter": ["Reiseführer", "Torture", "Instruments"]
  },
  {
    "titel": "Sie bauten eine Kathedrale",
    "autor": "David Macaulay",
    "sprache": "Deutsch",
    "schlagwörter": ["Bauten", "Kathedrale"]
  },
  {
    "titel": "Reyes y Reinas de España",
    "autor": "Unbekannt",
    "sprache": "Spanisch",
    "schlagwörter": ["Reinas", "España"]
  },
  {
    "titel": "Mac P. Lorne",
    "autor": "Mac P. Lorne",
    "sprache": "Deutsch",
    "schlagwörter": []
  },
  {
    "titel": "Gewehre für Interessierte, Liebhaber und Sammler",
    "autor": "Neuer Kaiser Verlag",
    "sprache": "Deutsch",
    "schlagwörter": ["Gewehre", "Interessierte", "Liebhaber", "Sammler"]
  },
  {
    "titel": "Altgriechische Technologie: Die Erfindungen der Griechen in der Antike",
    "autor": "Kostas Kotsanas",
    "sprache": "Deutsch",
    "schlagwörter": ["Altgriechische", "Technologie", "Erfindungen", "Griechen", "Antike"]
  },
  {
    "titel": "Der Dreißigjährige Krieg",
    "autor": "Herfried Münkler",
    "sprache": "Deutsch",
    "schlagwörter": ["Dreißigjährige"]
  },
  {
    "titel": "Instructions for British Servicemen in Germany",
    "autor": "The Foreign Office London",
    "sprache": "Englisch",
    "schlagwörter": ["Instructions", "British", "Servicemen", "Germany"]
  },
  {
    "titel": "German Invasion Plan for the British Isles",
    "autor": "Robert Wheeler",
    "sprache": "Englisch",
    "schlagwörter": ["German", "Invasion", "British"]
  },
  {
    "titel": "The British Home Guard Pocket Book",
    "autor": "Brig-Gen. A. F. U. Green",
    "sprache": "Englisch",
    "schlagwörter": ["British", "Home Guard", "Pocket"]
  },
  {
    "titel": "Secrets of Churchill's War Rooms",
    "autor": "Jonathan Asbury",
    "sprache": "Englisch",
    "schlagwörter": ["Secrets", "Churchill's"]
  },
  {
    "titel": "The Tower of London",
    "autor": "Guide",
    "sprache": "Englisch",
    "schlagwörter": ["Reiseführer", "London"]
  },
  {
    "titel": "The British Museum",
    "autor": "The British Museum",
    "sprache": "Spanisch",
    "schlagwörter": ["Museum", "British"]
  },
  {
    "titel": "Masterpieces of the British Museum",
    "autor": "The British Museum",
    "sprache": "Englisch",
    "schlagwörter": ["Museum", "Masterpieces", "British"]
  },
  {
    "titel": "Masterpieces of the Wallace Collection",
    "autor": "National Museum London",
    "sprache": "Englisch",
    "schlagwörter": ["Museum", "Masterpieces", "Wallace", "Collection"]
  },
  {
    "titel": "IWM London",
    "autor": "Guide",
    "sprache": "Englisch",
    "schlagwörter": ["Reiseführer", "London"]
  },
  {
    "titel": "The Tank Book: The Definitive Visual History of Armoured Vehicles",
    "autor": "The Tank Museum",
    "sprache": "Englisch",
    "schlagwörter": ["Waffen", "Rüstung", "Geschichte", "Museum", "Definitive", "Visual"]
  },
  {
    "titel": "World War Two Infographics",
    "autor": "Jonathan Fenby",
    "sprache": "Englisch",
    "schlagwörter": ["Weltkrieg", "Infographics"]
  },
  {
    "titel": "British India",
    "autor": "Michael Edwardes",
    "sprache": "Englisch",
    "schlagwörter": ["Indien", "British"]
  },
  {
    "titel": "The Indian Mutiny",
    "autor": "John Harris",
    "sprache": "Englisch",
    "schlagwörter": ["Indien", "Indian", "Mutiny"]
  },
  {
    "titel": "The Indian Mutiny of 1857",
    "autor": "G. B. Malleson",
    "sprache": "Englisch",
    "schlagwörter": ["Indien", "1857", "Sepoy-Aufstand", "Indian", "Mutiny"]
  },
  {
    "titel": "Spectre of Violence: The 1857 Kanpur Massacres",
    "autor": "Rudrangshu Mukherjee",
    "sprache": "Englisch",
    "schlagwörter": ["1857", "Sepoy-Aufstand", "Spectre", "Violence", "Kanpur", "Massacres"]
  },
  {
    "titel": "Mangal Pandey",
    "autor": "Rudrangshu Mukherjee",
    "sprache": "Englisch",
    "schlagwörter": ["Mangal", "Pandey"]
  },
  {
    "titel": "Reminiscences of the Great Mutiny",
    "autor": "W. F. Mitchell",
    "sprache": "Englisch",
    "schlagwörter": ["Reminiscences", "Mutiny"]
  },
  {
    "titel": "The Indian Mutiny",
    "autor": "Julian Spilsbury",
    "sprache": "Englisch",
    "schlagwörter": ["Indien", "Indian", "Mutiny"]
  },
  {
    "titel": "Private Life of the Mughals of India",
    "autor": "Nath",
    "sprache": "Englisch",
    "schlagwörter": ["Indien", "Private", "Mughals"]
  },
  {
    "titel": "Akbar and the Rise of the Mughal Empire",
    "autor": "G. B. Malleson",
    "sprache": "Englisch",
    "schlagwörter": ["Mughal", "Empire"]
  },
  {
    "titel": "Abenteuer Fernhandel",
    "autor": "Jürgen G. Nagel",
    "sprache": "Deutsch",
    "schlagwörter": ["Abenteuer", "Fernhandel"]
  },
  {
    "titel": "The Rise of Civilization in India and Pakistan",
    "autor": "Bridget and Raymond Allchin",
    "sprache": "Englisch",
    "schlagwörter": ["Indien", "Civilization", "Pakistan"]
  },
  {
    "titel": "Geschichte Indiens vom Mittelalter bis zur Gegenwart",
    "autor": "Dietmar Rothermund",
    "sprache": "Deutsch",
    "schlagwörter": ["Geschichte", "Indiens", "Mittelalter", "Gegenwart"]
  },
  {
    "titel": "A Calendar of the Court Minutes etc. of the East India Company",
    "autor": "Ethel Bruce Sainsbury",
    "sprache": "Englisch",
    "schlagwörter": ["Indien", "Calendar", "Minutes", "Indian", "Company"]
  },
  {
    "titel": "The Life of the Nawabs of Lucknow",
    "autor": "Ravi Bhatt",
    "sprache": "Englisch",
    "schlagwörter": ["Nawabs", "Lucknow"]
  },
  {
    "titel": "India's Wars: A Military History",
    "autor": "Arjun Subramaniam",
    "sprache": "Englisch",
    "schlagwörter": ["Kriegsgeschichte", "Geschichte", "India's", "Military", "History"]
  },
  {
    "titel": "Die Indoeuropäer: Aufbruch aus der Vorgeschichte",
    "autor": "Reinhard Schmoeckel",
    "sprache": "Deutsch",
    "schlagwörter": ["Indoeuropäer", "Aufbruch", "Vorgeschichte"]
  },
  {
    "titel": "Fischer Weltgeschichte",
    "autor": "Fischer Weltgeschichte",
    "sprache": "Deutsch",
    "schlagwörter": ["Fischer", "Weltgeschichte"]
  },
  {
    "titel": "The Arthashastra",
    "autor": "L. N. Rangarajan",
    "sprache": "Englisch",
    "schlagwörter": ["Arthashastra"]
  },
  {
    "titel": "The Decisive Battles of India",
    "autor": "George Bruce Malleson",
    "sprache": "Englisch",
    "schlagwörter": ["Indien", "Decisive", "Battles"]
  },
  {
    "titel": "Geschichte Indiens von der Induskultur bis heute",
    "autor": "Hermann Kulke und Dietmar Rothermund",
    "sprache": "Deutsch",
    "schlagwörter": ["Geschichte", "Indiens", "Induskultur"]
  },
  {
    "titel": "The Life and Times of the Nawabs of Lucknow",
    "autor": "Ravi Bhatt",
    "sprache": "Englisch",
    "schlagwörter": ["Nawabs", "Lucknow"]
  },
  {
    "titel": "Alexander der Große in Indien",
    "autor": "Johannes Hahn",
    "sprache": "Deutsch",
    "schlagwörter": ["Alexander", "Große", "Indien"]
  },
  {
    "titel": "The Fall of the Mughal Empire Volume 1, 2, 3, 4",
    "autor": "National Museum of Delhi",
    "sprache": "Englisch",
    "schlagwörter": ["Mughal", "Delhi", "Museum", "Empire", "Volume"]
  },
  {
    "titel": "Gazetteer of India",
    "autor": "Thorton",
    "sprache": "Englisch",
    "schlagwörter": ["Indien", "Gazetteer"]
  },
  {
    "titel": "India: A History",
    "autor": "John Keay",
    "sprache": "Englisch",
    "schlagwörter": ["Indien", "Geschichte", "History"]
  },
  {
    "titel": "Maharaja",
    "autor": "Ranjit Singh",
    "sprache": "Englisch",
    "schlagwörter": ["Maharaja"]
  },
  {
    "titel": "The Mughal Strategy of War",
    "autor": "Abdul Sabahuddin",
    "sprache": "Englisch",
    "schlagwörter": ["Mughal", "Strategy"]
  },
  {
    "titel": "Indian History",
    "autor": "Encyclopaedia Britannica",
    "sprache": "Englisch",
    "schlagwörter": ["Indien", "Geschichte", "Indian", "History"]
  },
  {
    "titel": "Delhi Fort: A Guide to the Buildings and Gardens",
    "autor": "Gordon Sanderson",
    "sprache": "Englisch",
    "schlagwörter": ["Delhi", "Reiseführer", "Buildings", "Gardens"]
  },
  {
    "titel": "The Mogul Emperors of Hindustan",
    "autor": "Edward S. Holden",
    "sprache": "Englisch",
    "schlagwörter": ["Hinduismus", "Emperors", "Hindustan"]
  },
  {
    "titel": "Asoka and the Decline of the Mauryas",
    "autor": "Romila Thapar",
    "sprache": "Englisch",
    "schlagwörter": ["Decline", "Mauryas"]
  },
  {
    "titel": "Das Britische Empire",
    "autor": "Der Spiegel",
    "sprache": "Deutsch",
    "schlagwörter": ["Britische", "Empire"]
  },
  {
    "titel": "The Dutch East India Company in India",
    "autor": "Bauke van der Pol",
    "sprache": "Englisch",
    "schlagwörter": ["Indien", "Company"]
  },
  {
    "titel": "The Bhagavad Gita",
    "autor": "Religion",
    "sprache": "Hindi",
    "schlagwörter": ["Bhagavad Gita"]
  },
  {
    "titel": "Illustrations of the History and Practices of the Thugs",
    "autor": "Thornton",
    "sprache": "Englisch",
    "schlagwörter": ["Thuggee/Kriminalität", "Geschichte", "Illustrations", "History", "Practices"]
  },
  {
    "titel": "Indian Caste System: A Study",
    "autor": "Hayavadana Rao",
    "sprache": "Englisch",
    "schlagwörter": ["Indien", "Indian", "System"]
  },
  {
    "titel": "The Last Mughal",
    "autor": "William Dalrymple",
    "sprache": "Englisch",
    "schlagwörter": ["Mughal"]
  },
  {
    "titel": "Empire of the Sikhs",
    "autor": "Maharaja Ranjit Singh",
    "sprache": "Englisch",
    "schlagwörter": ["Sikh", "Empire"]
  },
  {
    "titel": "Indien von den Anfängen bis zum Kolonialismus",
    "autor": "R. Thapar, P. Spear",
    "sprache": "Deutsch",
    "schlagwörter": ["Indien", "Anfängen", "Kolonialismus"]
  },
  {
    "titel": "The Indians: Portrait of a People",
    "autor": "Sudhir Kakar",
    "sprache": "Englisch",
    "schlagwörter": ["Indien", "Indians", "Portrait", "People"]
  },
  {
    "titel": "The Koh-i-Noor Diamond",
    "autor": "Iradj Amini",
    "sprache": "Englisch",
    "schlagwörter": ["Diamond"]
  },
  {
    "titel": "Thug: The True Story of India's Murderous Cult",
    "autor": "Mike Dash",
    "sprache": "Englisch",
    "schlagwörter": ["Indien", "Thuggee/Kriminalität", "India's", "Murderous"]
  },
  {
    "titel": "Confessions of a Thug",
    "autor": "Meadows Taylor",
    "sprache": "Englisch",
    "schlagwörter": ["Thuggee/Kriminalität", "Confessions"]
  },
  {
    "titel": "Confessions of a Thug",
    "autor": "Philip Meadows Taylor",
    "sprache": "Englisch",
    "schlagwörter": ["Thuggee/Kriminalität", "Confessions"]
  },
  {
    "titel": "India from Curzon to Nehru and After",
    "autor": "Durga Das",
    "sprache": "Englisch",
    "schlagwörter": ["Indien", "Curzon"]
  },
  {
    "titel": "An Era of Darkness: The British Empire in India",
    "autor": "Shashi Tharoor",
    "sprache": "Englisch",
    "schlagwörter": ["Indien", "Darkness", "British", "Empire"]
  },
  {
    "titel": "Kamasutra: Die Geheimnisse fernöstlicher Liebeskunst",
    "autor": "Bassermann",
    "sprache": "Deutsch",
    "schlagwörter": ["Erotik/Kultur", "Kamasutra", "Geheimnisse", "Fernöstlicher", "Liebeskunst"]
  },
  {
    "titel": "A Handbook for Visitors to Lucknow",
    "autor": "G. Keene",
    "sprache": "Englisch",
    "schlagwörter": ["Handbook", "Visitors", "Lucknow"]
  },
  {
    "titel": "Annals and Antiquities of Rajasthan",
    "autor": "James Tod",
    "sprache": "Englisch",
    "schlagwörter": ["Annals", "Antiquities", "Rajasthan"]
  },
  {
    "titel": "The Coins of India",
    "autor": "C. J. Brown",
    "sprache": "Englisch",
    "schlagwörter": ["Indien", "Numismatik"]
  },
  {
    "titel": "The Coins of Haidar Ali and Tipu Sultan",
    "autor": "J. R. Henderson",
    "sprache": "Englisch",
    "schlagwörter": ["Numismatik", "Haidar", "Sultan"]
  },
  {
    "titel": "Indian Numismatic Studies",
    "autor": "K. D. Bajpai",
    "sprache": "Englisch",
    "schlagwörter": ["Indien", "Numismatik", "Indian", "Numismatic", "Studies"]
  },
  {
    "titel": "The Coins of the Dutch East Indies",
    "autor": "John Bucknill",
    "sprache": "Englisch",
    "schlagwörter": ["Indien", "Numismatik", "Indies"]
  },
  {
    "titel": "Great Women of India",
    "autor": "Advaita Ashrama",
    "sprache": "Englisch",
    "schlagwörter": ["Indien"]
  },
  {
    "titel": "The Art of War",
    "autor": "Sun Tzu",
    "sprache": "Englisch",
    "schlagwörter": []
  },
  {
    "titel": "Islamic Weapons: Maghrib to Mughal",
    "autor": "Indigo",
    "sprache": "Englisch",
    "schlagwörter": ["Waffen", "Islamic", "Weapons", "Maghrib"]
  },
  {
    "titel": "Precious Indian Weapons and Other Princely Accoutrements",
    "autor": "Thames and Hudson",
    "sprache": "Englisch",
    "schlagwörter": ["Indien", "Waffen", "Precious", "Indian", "Weapons", "Princely"]
  },
  {
    "titel": "Catalogue of Edged Arms and Armour in the Salar Jung Museum Hyderabad",
    "autor": "G. N. Pant",
    "sprache": "Englisch",
    "schlagwörter": ["Waffen", "Rüstung", "Museum", "Catalogue", "Armour", "Salar Jung"]
  },
  {
    "titel": "Indian and Oriental Arms and Armour",
    "autor": "Lord Egerton of Tatton",
    "sprache": "Englisch",
    "schlagwörter": ["Indien", "Waffen", "Rüstung", "Indian", "Oriental", "Armour"]
  },
  {
    "titel": "Indian Armours in the National Museum Collection",
    "autor": "G. N. Pant and K. K. Sharma",
    "sprache": "Englisch",
    "schlagwörter": ["Indien", "Waffen", "Rüstung", "Museum", "Indian", "Armours"]
  },
  {
    "titel": "Indian Armour in Battle: The First Seventy-Five Years",
    "autor": "Col. Puneet Tewari",
    "sprache": "Englisch",
    "schlagwörter": ["Indien", "Waffen", "Rüstung", "Indian", "Armour", "Battle"]
  },
  {
    "titel": "Oriental Armour",
    "autor": "H. Russell Robinson",
    "sprache": "Englisch",
    "schlagwörter": ["Waffen", "Rüstung", "Oriental", "Armour"]
  },
  {
    "titel": "Arms and Armour: Traditional Weapons of India",
    "autor": "Jaiwant Paul",
    "sprache": "Englisch",
    "schlagwörter": ["Indien", "Waffen", "Rüstung", "Armour", "Traditional", "Weapons"]
  },
  {
    "titel": "The Tipu Sultan Collection",
    "autor": "Sotheby's",
    "sprache": "Englisch",
    "schlagwörter": ["Sultan", "Collection"]
  },
  {
    "titel": "By My Sword and Shield: Traditional Weapons of the Indian Warrior",
    "autor": "E. Jaiwant Paul",
    "sprache": "Englisch",
    "schlagwörter": ["Indien", "Waffen", "Shield", "Traditional", "Weapons", "Indian"]
  },
  {
    "titel": "Where Stones Speak",
    "autor": "Rana Safvi",
    "sprache": "Englisch",
    "schlagwörter": ["Stones"]
  },
  {
    "titel": "The Indian Sepoy Soldier of the Raj",
    "autor": "Col. Ranjit Sengupta",
    "sprache": "Englisch",
    "schlagwörter": ["Indien", "Indian", "Sepoy", "Soldier"]
  },
  {
    "titel": "Museum of Rajasthan",
    "autor": "Jawahar Kala Kendra",
    "sprache": "Englisch",
    "schlagwörter": ["Museum", "Rajasthan"]
  },
  {
    "titel": "The British Indian Army",
    "autor": "Peter Duckers",
    "sprache": "Englisch",
    "schlagwörter": ["Indien", "Waffen", "British", "Indian"]
  },
  {
    "titel": "Tropas de Élite de India y Pakistán",
    "autor": "Osprey Military",
    "sprache": "Spanisch",
    "schlagwörter": ["Indien", "Tropas", "Pakistán"]
  },
  {
    "titel": "The Sikh Army 1799-1849",
    "autor": "Ian Heath",
    "sprache": "Englisch",
    "schlagwörter": ["Sikh", "Waffen"]
  },
  {
    "titel": "British Military Rifles",
    "autor": "Peter Duckers",
    "sprache": "Englisch",
    "schlagwörter": ["British", "Military", "Rifles"]
  },
  {
    "titel": "The Indian Mutiny",
    "autor": "Christopher Wilkinson-Latham",
    "sprache": "Englisch",
    "schlagwörter": ["Indien", "Indian", "Mutiny"]
  },
  {
    "titel": "\"If I Die Here, Who Will Remember Us\": India and the First World War",
    "autor": "Vedica Kant",
    "sprache": "Englisch",
    "schlagwörter": ["Indien", "Weltkrieg", "Remember"]
  },
  {
    "titel": "The Theft of India: The European Conquest of India 1498-1765",
    "autor": "Roy Moxham",
    "sprache": "Englisch",
    "schlagwörter": ["Indien", "European", "Conquest"]
  },
  {
    "titel": "The Indian Army: Its Contribution to the Development of a Nation",
    "autor": "Stephen P. Cohen",
    "sprache": "Englisch",
    "schlagwörter": ["Indien", "Waffen", "Indian", "Contribution", "Development", "Nation"]
  },
  {
    "titel": "Jallianwala Bagh, 1919: The Real Story",
    "autor": "Kishwar Desai",
    "sprache": "Englisch",
    "schlagwörter": ["Jallianwala"]
  },
  {
    "titel": "Delhi Top Heritage: Top 10 Baolis",
    "autor": "Vikramjit Singh Rooprai",
    "sprache": "Englisch",
    "schlagwörter": ["Delhi", "Heritage", "Baolis"]
  },
  {
    "titel": "The Rani of Jhansi",
    "autor": "D. V. Tahmankar",
    "sprache": "Englisch",
    "schlagwörter": ["Jhansi"]
  },
  {
    "titel": "Aurangzeb: The Man and the Myth",
    "autor": "Audrey Truschke",
    "sprache": "Englisch",
    "schlagwörter": ["Aurangzeb"]
  },
  {
    "titel": "A Survey of Kerala History",
    "autor": "A. Sreedhara Menon",
    "sprache": "Englisch",
    "schlagwörter": ["Geschichte", "Survey", "Kerala", "History"]
  },
  {
    "titel": "Rajasthan: Das Indien der Maharadschas",
    "autor": "Amina Okada",
    "sprache": "Deutsch",
    "schlagwörter": ["Rajasthan", "Indien", "Maharadschas"]
  },
  {
    "titel": "Indien Interieurs",
    "autor": "Angelika Taschen",
    "sprache": "Deutsch",
    "schlagwörter": ["Indien", "Interieurs"]
  },
  {
    "titel": "Forts and Palaces of India",
    "autor": "Bindu Manchanda",
    "sprache": "Englisch",
    "schlagwörter": ["Indien", "Palaces"]
  },
  {
    "titel": "This Is India",
    "autor": "Shobita Punja",
    "sprache": "Englisch",
    "schlagwörter": ["Indien"]
  },
  {
    "titel": "History of Medieval India: Sultanate Period and Mughal Period",
    "autor": "V. D. Mahajan",
    "sprache": "Englisch",
    "schlagwörter": ["Indien", "Mughal", "Geschichte", "History", "Medieval", "Sultanate"]
  },
  {
    "titel": "Culture Shock India",
    "autor": "Gitanjali Kolanad",
    "sprache": "Englisch",
    "schlagwörter": ["Indien", "Culture"]
  },
  {
    "titel": "Zeit für Indien: 30 Traumziele zum Wohlfühlen",
    "autor": "Bucher",
    "sprache": "Deutsch",
    "schlagwörter": ["Indien", "Traumziele", "Wohlfühlen"]
  },
  {
    "titel": "Indien: Götter und Kosmos - Karma und Erleuchtung - Meditation und Yoga",
    "autor": "Richard Waterstone",
    "sprache": "Deutsch",
    "schlagwörter": ["Indien", "Götter", "Kosmos", "Erleuchtung", "Meditation"]
  },
  {
    "titel": "The Far Pavilions",
    "autor": "M. M. Kaye",
    "sprache": "Englisch",
    "schlagwörter": ["Pavilions"]
  },
  {
    "titel": "Vanamali Gunturu: Hinduismus",
    "autor": "Diederichs",
    "sprache": "Deutsch",
    "schlagwörter": ["Hinduismus", "Vanamali", "Gunturu"]
  },
  {
    "titel": "Aum Pranayama: Its Philosophy and Practice",
    "autor": "Swami Ramdevji Maharaj",
    "sprache": "Englisch",
    "schlagwörter": ["Pranayama", "Philosophy", "Practice"]
  },
  {
    "titel": "Salman Rushdie: Des Mauren letzter Seufzer (Roman)",
    "autor": "Gisela Stege",
    "sprache": "Deutsch",
    "schlagwörter": ["Salman", "Rushdie", "Mauren", "Letzter", "Seufzer"]
  },
  {
    "titel": "Aus Indien",
    "autor": "Sev. Moti S.J.",
    "sprache": "Deutsch",
    "schlagwörter": ["Indien"]
  },
  {
    "titel": "Im Auftrag des Syndikats",
    "autor": "Berkely Mather",
    "sprache": "Deutsch",
    "schlagwörter": ["Auftrag", "Syndikats"]
  },
  {
    "titel": "Die Gärten der Liebe: Erotische Geschichten aus Indien",
    "autor": "Roland Beer",
    "sprache": "Deutsch",
    "schlagwörter": ["Gärten", "Erotische", "Geschichten", "Indien"]
  },
  {
    "titel": "Book of Hindu Names",
    "autor": "Maneka Gandhi",
    "sprache": "Englisch",
    "schlagwörter": ["Hinduismus"]
  },
  {
    "titel": "The Holy Cow and Other Indian Stories",
    "autor": "Tarun Chopra",
    "sprache": "Englisch",
    "schlagwörter": ["Stories"]
  },
  {
    "titel": "Hinduismus erleben",
    "autor": "Rainer Krack",
    "sprache": "Deutsch",
    "schlagwörter": ["Hinduismus", "Erleben"]
  },
  {
    "titel": "What Happens to Gods and Demons",
    "autor": "H. N. Verma and Amrit Verma",
    "sprache": "Englisch",
    "schlagwörter": ["Happens", "Demons"]
  },
  {
    "titel": "A Passage to India",
    "autor": "E. M. Forster",
    "sprache": "Englisch",
    "schlagwörter": ["Indien", "Passage"]
  },
  {
    "titel": "Wer den Weg der Wahrheit geht, stolpert nicht",
    "autor": "Mahatma Gandhi",
    "sprache": "Deutsch",
    "schlagwörter": ["Wahrheit", "Stolpert"]
  },
  {
    "titel": "The Anarchy: The East India Company, Corporate Violence and the Pillage of an Empire",
    "autor": "William Dalrymple",
    "sprache": "Englisch",
    "schlagwörter": ["Indien", "Anarchy", "Company", "Corporate", "Violence", "Pillage"]
  },
  {
    "titel": "Themes in Indian History: The Mughal State 1526-1750",
    "autor": "Oxford India Paperbacks",
    "sprache": "Englisch",
    "schlagwörter": ["Indien", "Mughal", "Geschichte", "Themes", "Indian", "History"]
  },
  {
    "titel": "Ancient India: New Research",
    "autor": "Upinder Singh and Nayanjot Lahiri",
    "sprache": "Englisch",
    "schlagwörter": ["Indien", "Ancient", "Research"]
  },
  {
    "titel": "Weekend Breaks from Hyderabad",
    "autor": "Outlook Traveller",
    "sprache": "Englisch",
    "schlagwörter": ["Weekend", "Breaks", "Hyderabad"]
  },
  {
    "titel": "Kautilya: The Arthashastra",
    "autor": "Penguin Classics",
    "sprache": "Englisch",
    "schlagwörter": ["Kautilya", "Arthashastra"]
  },
  {
    "titel": "Lucknow: Delhi - A Thousand Years of Building",
    "autor": "Lotus Roli",
    "sprache": "Englisch",
    "schlagwörter": ["Delhi", "Thousand", "Building"]
  },
  {
    "titel": "Footprint 1st Edition: Rajasthan and Gujarat Handbook",
    "autor": "Robert and Roma Bradnock",
    "sprache": "Englisch",
    "schlagwörter": ["Footprint", "Edition", "Rajasthan", "Gujarat", "Handbook"]
  },
  {
    "titel": "India: The Bestselling Guide to the Subcontinent",
    "autor": "Lonely Planet",
    "sprache": "Englisch",
    "schlagwörter": ["Indien", "Reiseführer", "Bestselling", "Subcontinent"]
  },
  {
    "titel": "Kerala",
    "autor": "Lonely Planet",
    "sprache": "Englisch",
    "schlagwörter": ["Kerala"]
  },
  {
    "titel": "Indian Geography: A Historical Perspective",
    "autor": "P. L. Madan",
    "sprache": "Englisch",
    "schlagwörter": ["Indien", "Indian", "Geography", "Historical", "Perspective"]
  },
  {
    "titel": "Elephanta",
    "autor": "George Michell",
    "sprache": "Englisch",
    "schlagwörter": ["Elephanta"]
  },
  {
    "titel": "Footprint 11th India",
    "autor": "Robert and Roma Bradnock",
    "sprache": "Englisch",
    "schlagwörter": ["Indien", "Footprint"]
  },
  {
    "titel": "Footprint 13th Edition India",
    "autor": "Robert and Roma Bradnock",
    "sprache": "Englisch",
    "schlagwörter": ["Indien", "Footprint", "Edition"]
  },
  {
    "titel": "A Field Guide to Indian Mammals",
    "autor": "Vivek Menon",
    "sprache": "Englisch",
    "schlagwörter": ["Indien", "Reiseführer", "Indian", "Mammals"]
  },
  {
    "titel": "Die Geschichte Mallorcas",
    "autor": "Thomas Freller",
    "sprache": "Deutsch",
    "schlagwörter": ["Geschichte", "Mallorcas"]
  },
  {
    "titel": "The First Punjab War",
    "autor": "Shah Mohammed's Jangnamah",
    "sprache": "Englisch",
    "schlagwörter": ["Punjab"]
  },
  {
    "titel": "4000 Jahre Pfahlbauten",
    "autor": "Thorbecke",
    "sprache": "Deutsch",
    "schlagwörter": ["Pfahlbauten"]
  },
  {
    "titel": "South India: Temple Towns and Tropical Beaches",
    "autor": "Lonely Planet",
    "sprache": "Englisch",
    "schlagwörter": ["Indien", "Tempel/Architektur", "Temple", "Tropical", "Beaches"]
  },
  {
    "titel": "India 2004",
    "autor": "Observer Statistical Handbook",
    "sprache": "Englisch",
    "schlagwörter": ["Indien"]
  },
  {
    "titel": "Monuments and Sights in Haryana",
    "autor": "Archaeological Survey of India",
    "sprache": "Englisch",
    "schlagwörter": ["Indien", "Monuments", "Sights", "Haryana"]
  },
  {
    "titel": "Delhi and Its Neighbourhood",
    "autor": "Archaeological Survey of India",
    "sprache": "Englisch",
    "schlagwörter": ["Indien", "Delhi", "Neighbourhood"]
  },
  {
    "titel": "Qutb Minar and Adjoining Monuments",
    "autor": "Archaeological Survey of India",
    "sprache": "Englisch",
    "schlagwörter": ["Indien", "Adjoining", "Monuments"]
  },
  {
    "titel": "Temples of India",
    "autor": "Salim Pushpanath",
    "sprache": "Englisch",
    "schlagwörter": ["Indien", "Tempel/Architektur", "Temples"]
  },
  {
    "titel": "Dreamlands Atlas of India",
    "autor": "Dreamland",
    "sprache": "Englisch",
    "schlagwörter": ["Indien", "Dreamlands"]
  },
  {
    "titel": "Enigmas de la Arqueología Balear",
    "autor": "Javier Aramburu-Zabala",
    "sprache": "Spanisch",
    "schlagwörter": ["Enigmas", "Arqueología", "Balear"]
  },
  {
    "titel": "Der Hexenhammer",
    "autor": "Heinrich Kramer",
    "sprache": "Deutsch",
    "schlagwörter": ["Hexenhammer"]
  },
  {
    "titel": "The Armies of India",
    "autor": "G. F. MacMunn",
    "sprache": "Englisch",
    "schlagwörter": ["Indien", "Waffen", "Militärgeschichte", "Armies"]
  },
  {
    "titel": "Ancient Delhi - Second Edition",
    "autor": "Upinder Singh",
    "sprache": "Englisch",
    "schlagwörter": ["Delhi", "Ancient", "Second", "Edition"]
  },
  {
    "titel": "15.000 Jahre Mord und Totschlag: Anthropologen auf der Spur spektakulärer Verbrechen",
    "autor": "Joachim Wahl",
    "sprache": "Deutsch",
    "schlagwörter": ["Totschlag", "Anthropologen", "Spektakulärer", "Verbrechen"]
  },
  {
    "titel": "Denkmalpflege und Archäologie im Kanton St. Gallen 2004-2008",
    "autor": "Amt für Kultur des Kantons St. Gallen",
    "sprache": "Deutsch",
    "schlagwörter": ["Denkmalpflege", "Archäologie", "Kanton", "Gallen"]
  },
  {
    "titel": "Ritter und Rüstungen",
    "autor": "Terence Wise",
    "sprache": "Deutsch",
    "schlagwörter": ["Ritter", "Rüstungen"]
  },
  {
    "titel": "British Iron Heavy Ordnance",
    "autor": "Ken Trotman",
    "sprache": "Englisch",
    "schlagwörter": ["British", "Ordnance"]
  },
  {
    "titel": "Keith Dowen",
    "autor": "Keith Dowen",
    "sprache": "Englisch",
    "schlagwörter": []
  },
  {
    "titel": "Old Delhi: 10 Easy Walks",
    "autor": "Gaynor Barton",
    "sprache": "Englisch",
    "schlagwörter": ["Delhi"]
  },
  {
    "titel": "Das Strafrecht des Sachsenspiegels",
    "autor": "Viktor Friese",
    "sprache": "Deutsch",
    "schlagwörter": ["Strafrecht", "Sachsenspiegel"]
  },
  {
    "titel": "A Mediterranean Emporium: The Catalan Kingdom of Majorca",
    "autor": "David Abulafia",
    "sprache": "Englisch",
    "schlagwörter": ["Mediterranean", "Emporium", "Catalan", "Kingdom", "Majorca"]
  },
  {
    "titel": "Kauderwelsch Band 17",
    "autor": "Kauderwelsch Band 17",
    "sprache": "Deutsch",
    "schlagwörter": ["Kauderwelsch"]
  },
  {
    "titel": "Language Guide",
    "autor": "Language Guide",
    "sprache": "Englisch",
    "schlagwörter": ["Reiseführer", "Language"]
  },
  {
    "titel": "Museums of India - Second Edition",
    "autor": "Shobita Punja",
    "sprache": "Englisch",
    "schlagwörter": ["Indien", "Museum", "Museums", "Second", "Edition"]
  },
  {
    "titel": "Die Geschichte des Dritten Reiches",
    "autor": "Joachim C. Fest",
    "sprache": "Deutsch",
    "schlagwörter": ["Geschichte", "Dritten", "Reiches"]
  },
  {
    "titel": "Europa im Krieg 1939-1945: Kollaboration und Widerstand",
    "autor": "Werner Rings",
    "sprache": "Deutsch",
    "schlagwörter": ["Europa", "Kollaboration", "Widerstand"]
  },
  {
    "titel": "Vom Sonderbund zum Bundesstaat: Krise und Erneuerung 1798-1848 im Spiegel der NZZ",
    "autor": "Thomas Maissen",
    "sprache": "Deutsch",
    "schlagwörter": ["Sonderbund", "Bundesstaat", "Krise", "Erneuerung", "Spiegel"]
  },
  {
    "titel": "French Army Museum: Contemporary Department 1871-1945",
    "autor": "Artlys",
    "sprache": "Englisch",
    "schlagwörter": ["Waffen", "Museum", "French", "Contemporary", "Department"]
  },
  {
    "titel": "Arms and Armour from St. Louis to Louis XIII",
    "autor": "Treasures of the Historic Collection; Musée de l'Armée",
    "sprache": "Englisch",
    "schlagwörter": ["Waffen", "Rüstung", "Armour"]
  },
  {
    "titel": "The Invalides",
    "autor": "The Army Museum - The Tomb of Napoleon",
    "sprache": "Englisch",
    "schlagwörter": ["Waffen", "Napoleon", "Museum", "Invalides"]
  },
  {
    "titel": "National Museum of the Châteaux de Malmaison et de Bois-Préau",
    "autor": "Museum Guide",
    "sprache": "Englisch",
    "schlagwörter": ["Reiseführer", "Museum", "National", "Malmaison"]
  },
  {
    "titel": "1812: Napoleons Feldzug in Russland",
    "autor": "C. H. Beck",
    "sprache": "Deutsch",
    "schlagwörter": ["Napoleon", "Napoleons", "Feldzug", "Russland"]
  },
  {
    "titel": "Formen des Krieges 1600-1815",
    "autor": "Bayerischen Armeemuseum",
    "sprache": "Deutsch",
    "schlagwörter": ["Waffen", "Museum", "Formen", "Krieges"]
  },
  {
    "titel": "Salvador de Madariaga: Kolumbus",
    "autor": "Scherz",
    "sprache": "Deutsch",
    "schlagwörter": ["Salvador", "Madariaga", "Kolumbus"]
  },
  {
    "titel": "Der Kampf ums Paradies: Eine islamische Geschichte der Kreuzzüge",
    "autor": "Paul M. Cobb",
    "sprache": "Deutsch",
    "schlagwörter": ["Paradies", "Islamische", "Geschichte", "Kreuzzüge"]
  },
  {
    "titel": "Rifles",
    "autor": "Jim Supica and Doug Wicklund",
    "sprache": "Englisch",
    "schlagwörter": ["Rifles"]
  },
  {
    "titel": "The Complete World Encyclopedia of Knives, Swords, Spears and Daggers",
    "autor": "Hermes House",
    "sprache": "Englisch",
    "schlagwörter": ["Complete", "Encyclopedia", "Knives", "Swords", "Spears", "Daggers"]
  },
  {
    "titel": "Atlas Ilustrado de Armas Blancas",
    "autor": "Susaeta",
    "sprache": "Spanisch",
    "schlagwörter": ["Waffen", "Ilustrado", "Blancas"]
  },
  {
    "titel": "Atlas Ilustrado de la Guardia Civil",
    "autor": "Susaeta",
    "sprache": "Spanisch",
    "schlagwörter": ["Ilustrado", "Guardia"]
  },
  {
    "titel": "Atlas Ilustrado de Armas de Fuego",
    "autor": "Susaeta",
    "sprache": "Spanisch",
    "schlagwörter": ["Waffen", "Ilustrado"]
  },
  {
    "titel": "Antique Weapons for Pleasure and Investment",
    "autor": "Richard Akehurst",
    "sprache": "Englisch",
    "schlagwörter": ["Waffen", "Antique", "Weapons", "Pleasure", "Investment"]
  },
  {
    "titel": "The Complete Encyclopedia of Guns",
    "autor": "Hermes House",
    "sprache": "Englisch",
    "schlagwörter": ["Complete", "Encyclopedia"]
  },
  {
    "titel": "Britische Schalldämpferwaffen 1939-1945",
    "autor": "Wolfgang Michael",
    "sprache": "Deutsch",
    "schlagwörter": ["Britische", "Schalldämpferwaffen"]
  },
  {
    "titel": "Kunst- und Antiquitätenauktion: Antike Waffen und Militaria",
    "autor": "Fischer",
    "sprache": "Deutsch",
    "schlagwörter": ["Antiquitätenauktion", "Antike", "Waffen", "Militaria"]
  },
  {
    "titel": "Handfeuerwaffen des 20. und 21. Jahrhunderts",
    "autor": "Kaiser (Verlag)",
    "sprache": "Deutsch",
    "schlagwörter": ["Handfeuerwaffen", "Jahrhunderts"]
  },
  {
    "titel": "Illustrierte Pistolen- und Revolver-Enzyklopädie",
    "autor": "A. E. Hartink",
    "sprache": "Deutsch",
    "schlagwörter": ["Illustrierte", "Pistolen", "Revolver", "Enzyklopädie"]
  },
  {
    "titel": "Militärgewehre Enzyklopädie",
    "autor": "A. E. Hartink",
    "sprache": "Deutsch",
    "schlagwörter": ["Militärgewehre", "Enzyklopädie"]
  },
  {
    "titel": "The Complete Encyclopedia of Rifles and Carbines",
    "autor": "A. E. Hartink",
    "sprache": "Englisch",
    "schlagwörter": ["Complete", "Encyclopedia", "Rifles", "Carbines"]
  },
  {
    "titel": "Ultimate Handguns",
    "autor": "David Miller",
    "sprache": "Englisch",
    "schlagwörter": ["Ultimate", "Handguns"]
  },
  {
    "titel": "Pistolen und Revolver",
    "autor": "Kaiser",
    "sprache": "Deutsch",
    "schlagwörter": ["Pistolen", "Revolver"]
  },
  {
    "titel": "Gewehre für Interessierte, Liebhaber und Sammler",
    "autor": "Kaiser",
    "sprache": "Deutsch",
    "schlagwörter": ["Gewehre", "Interessierte", "Liebhaber", "Sammler"]
  },
  {
    "titel": "The Complete Encyclopedia of Hunting Rifles",
    "autor": "A. E. Hartink",
    "sprache": "Englisch",
    "schlagwörter": ["Complete", "Encyclopedia", "Hunting", "Rifles"]
  },
  {
    "titel": "Herrschaft und soziale Systeme in der frühen Neuzeit",
    "autor": "Jan Peters",
    "sprache": "Deutsch",
    "schlagwörter": ["Herrschaft", "Soziale", "Systeme", "Frühen", "Neuzeit"]
  },
  {
    "titel": "Legionär in der römischen Armee: Der ultimative Karriere-Führer",
    "autor": "Philip Matyszak",
    "sprache": "Deutsch",
    "schlagwörter": ["Waffen", "Legionär", "Römischen", "Ultimative", "Karriere", "Führer"]
  },
  {
    "titel": "Great Military Disasters",
    "autor": "Michael Haskew",
    "sprache": "Englisch",
    "schlagwörter": ["Military", "Disasters"]
  },
  {
    "titel": "Gewehre",
    "autor": "Kaiser",
    "sprache": "Deutsch",
    "schlagwörter": ["Gewehre"]
  },
  {
    "titel": "Handfeuerwaffen",
    "autor": "Kaiser",
    "sprache": "Deutsch",
    "schlagwörter": ["Handfeuerwaffen"]
  },
  {
    "titel": "Las Pistolas Astra",
    "autor": "Luc Guillou und Philippe Gourio",
    "sprache": "Spanisch",
    "schlagwörter": ["Pistolas"]
  },
  {
    "titel": "Las Pistolas Beretta",
    "autor": "Michel Malherbe",
    "sprache": "Spanisch",
    "schlagwörter": ["Pistolas", "Beretta"]
  },
  {
    "titel": "TIKAL",
    "autor": "TIKAL",
    "sprache": "Spanisch",
    "schlagwörter": []
  },
  {
    "titel": "Der große historische Atlas der Ritter und Burgen",
    "autor": "Ian Barnes",
    "sprache": "Deutsch",
    "schlagwörter": ["Große", "Historische", "Ritter", "Burgen"]
  },
  {
    "titel": "Catálogo de Arcabucería Madrileña 1687-1833",
    "autor": "Real Armería de Madrid",
    "sprache": "Spanisch",
    "schlagwörter": ["Catálogo", "Arcabucería", "Madrileña"]
  },
  {
    "titel": "Feuerwaffen: Entwicklung und Geschichte",
    "autor": "Dudley Pope",
    "sprache": "Deutsch",
    "schlagwörter": ["Feuerwaffen", "Entwicklung", "Geschichte"]
  },
  {
    "titel": "Waffen Digest 2009",
    "autor": "Stocker-Schmid Verlag und Motorbuch Verlag",
    "sprache": "Deutsch",
    "schlagwörter": ["Waffen", "Digest"]
  },
  {
    "titel": "Geschichte der Waffen vom Altertum bis heute",
    "autor": "Richard Holmes",
    "sprache": "Deutsch",
    "schlagwörter": ["Geschichte", "Waffen", "Altertum"]
  },
  {
    "titel": "Pistols, Revolvers and Submachine Guns",
    "autor": "Will Fowler, Anthony North and Charles Stronge",
    "sprache": "Englisch",
    "schlagwörter": ["Pistols", "Revolvers", "Submachine"]
  },
  {
    "titel": "Krieger, Kämpfer und Soldaten von der Antike bis heute",
    "autor": "R. C. Grant",
    "sprache": "Deutsch",
    "schlagwörter": ["Krieger", "Kämpfer", "Soldaten", "Antike"]
  },
  {
    "titel": "Firearms: The Illustrated Guide to Small Arms of the World",
    "autor": "Paragon Books",
    "sprache": "Englisch",
    "schlagwörter": ["Waffen", "Reiseführer", "Firearms", "Illustrated"]
  },
  {
    "titel": "The World Encyclopedia of Rifles and Machine Guns",
    "autor": "Will Fowler and Patrick Sweeney",
    "sprache": "Englisch",
    "schlagwörter": ["Encyclopedia", "Rifles", "Machine"]
  },
  {
    "titel": "Im Dienste Ihrer Majestät",
    "autor": "Bernd Rolff",
    "sprache": "Deutsch",
    "schlagwörter": ["Dienste", "Majestät"]
  },
  {
    "titel": "The World's Great Guns",
    "autor": "Frederick Wilkinson",
    "sprache": "Englisch",
    "schlagwörter": ["World's"]
  },
  {
    "titel": "Waffenenzyklopädie: 7000 Jahre Waffengeschichte",
    "autor": "David Harding",
    "sprache": "Deutsch",
    "schlagwörter": ["Waffenenzyklopädie", "Waffengeschichte"]
  },
  {
    "titel": "Schwarzpulver-Digest",
    "autor": "Jan Boger",
    "sprache": "Deutsch",
    "schlagwörter": ["Schwarzpulver-Digest"]
  },
  {
    "titel": "Schlachten des Zweiten Weltkriegs",
    "autor": "Mehere",
    "sprache": "Deutsch",
    "schlagwörter": ["Schlachten", "Zweiten", "Weltkriegs"]
  },
  {
    "titel": "Die Geschichte der Kreuzzüge",
    "autor": "Angus Konstam",
    "sprache": "Deutsch",
    "schlagwörter": ["Geschichte", "Kreuzzüge"]
  },
  {
    "titel": "Weapons and Technology of World War II",
    "autor": "Windsor Chorlton",
    "sprache": "Englisch",
    "schlagwörter": ["Waffen", "Weltkrieg", "Weapons", "Technology"]
  },
  {
    "titel": "Die illustrierte Geschichte der Waffen: Von der Steinaxt bis zum Maschinengewehr",
    "autor": "Bassermann",
    "sprache": "Deutsch",
    "schlagwörter": ["Illustrierte", "Geschichte", "Waffen", "Steinaxt", "Maschinengewehr"]
  },
  {
    "titel": "The Empire of Death",
    "autor": "Thames and Hudson",
    "sprache": "Englisch",
    "schlagwörter": ["Empire"]
  },
  {
    "titel": "Dumonts Enzyklopädie der Seefahrer und Entdecker: Von Amundsen bis zum Zeppelin",
    "autor": "Monte von Dumont",
    "sprache": "Deutsch",
    "schlagwörter": ["Dumonts", "Enzyklopädie", "Seefahrer", "Entdecker", "Amundsen", "Zeppelin"]
  },
  {
    "titel": "Militärgeschichte: Waffen und Kriegführung von der Antike bis heute",
    "autor": "DK",
    "sprache": "Deutsch",
    "schlagwörter": ["Militärgeschichte", "Waffen", "Kriegführung", "Antike"]
  },
  {
    "titel": "Waffen Digest 2008",
    "autor": "Verlag Stocker-Schmid und Motorbuch Verlag",
    "sprache": "Deutsch",
    "schlagwörter": ["Waffen", "Digest"]
  },
  {
    "titel": "Krieger, Kämpfer und Soldaten von der Antike bis heute",
    "autor": "R. G. Grant",
    "sprache": "Deutsch",
    "schlagwörter": ["Krieger", "Kämpfer", "Soldaten", "Antike"]
  },
  {
    "titel": "Großer Atlas der Entdeckungen",
    "autor": "Naumann und Göbel",
    "sprache": "Deutsch",
    "schlagwörter": ["Großer", "Entdeckungen"]
  },
  {
    "titel": "Kriege und Schlachten: 5000 Jahre Militärgeschichte",
    "autor": "R. G. Grant",
    "sprache": "Deutsch",
    "schlagwörter": ["Kriege", "Schlachten", "Militärgeschichte"]
  },
  {
    "titel": "Der Mensch des Mittelalters",
    "autor": "Jacques Le Goff",
    "sprache": "Deutsch",
    "schlagwörter": ["Mensch", "Mittelalters"]
  },
  {
    "titel": "Überall ist Mittelalter",
    "autor": "Horst Fuhrmann",
    "sprache": "Deutsch",
    "schlagwörter": ["Überall", "Mittelalter"]
  },
  {
    "titel": "Christoph Columbus: Eine Biographie",
    "autor": "Gianni Granzotto",
    "sprache": "Deutsch",
    "schlagwörter": ["Christoph", "Columbus", "Biographie"]
  },
  {
    "titel": "Die Reconquista: Christen und Muslime auf der iberischen Halbinsel 711-1492",
    "autor": "Nikolas Jaspert",
    "sprache": "Deutsch",
    "schlagwörter": ["Reconquista", "Christen", "Muslime", "Iberischen", "Halbinsel"]
  },
  {
    "titel": "Fischer Weltgeschichte Antike Band 1",
    "autor": "Fischer",
    "sprache": "Deutsch",
    "schlagwörter": ["Fischer", "Weltgeschichte", "Antike"]
  },
  {
    "titel": "Fischer Weltgeschichte Antike Band 2",
    "autor": "Fischer",
    "sprache": "Deutsch",
    "schlagwörter": ["Fischer", "Weltgeschichte", "Antike"]
  },
  {
    "titel": "Fischer Weltgeschichte Antike Band 3",
    "autor": "Fischer",
    "sprache": "Deutsch",
    "schlagwörter": ["Fischer", "Weltgeschichte", "Antike"]
  },
  {
    "titel": "Fischer Weltgeschichte Antike Band 4",
    "autor": "Fischer",
    "sprache": "Deutsch",
    "schlagwörter": ["Fischer", "Weltgeschichte", "Antike"]
  },
  {
    "titel": "Das Familienbuch Hans Volger des Älteren und des Jüngeren aus dem St. Galler Rheintal",
    "autor": "Alexa Renggli",
    "sprache": "Deutsch",
    "schlagwörter": ["Familienbuch", "Volger", "Älteren", "Jüngeren", "Galler", "Rheintal"]
  },
  {
    "titel": "Cicero und die römische Republik: Eine Biographie",
    "autor": "Manfred Fuhrmann",
    "sprache": "Deutsch",
    "schlagwörter": ["Cicero", "Römische", "Republik", "Biographie"]
  },
  {
    "titel": "The Book of Deeds of James I of Aragon",
    "autor": "Damian J. Smith and Helena Buffery",
    "sprache": "Englisch",
    "schlagwörter": ["Aragon"]
  },
  {
    "titel": "DTV-Atlas Weltgeschichte",
    "autor": "DTV",
    "sprache": "Deutsch",
    "schlagwörter": ["Weltgeschichte"]
  },
  {
    "titel": "Karte der Kulturgüter mit Verzeichnis und Detailkarten Schweiz",
    "autor": "Bundesamt für Landestopographie 3084 Wabern",
    "sprache": "Deutsch",
    "schlagwörter": ["Kulturgüter", "Verzeichnis", "Detailkarten", "Schweiz"]
  },
  {
    "titel": "Die Kreuzzüge",
    "autor": "Robert Payne",
    "sprache": "Deutsch",
    "schlagwörter": ["Kreuzzüge"]
  },
  {
    "titel": "Geköpft und gepfählt: Archäologen auf der Jagd nach den Untoten",
    "autor": "Angelika Franz / Daniel Nösler",
    "sprache": "Deutsch",
    "schlagwörter": ["Geköpft", "Gepfählt", "Archäologen", "Untoten"]
  },
  {
    "titel": "50 Klassiker Archäologie: Die wichtigsten Fundorte und Ausgrabungsstätten",
    "autor": "Wolfgang Korn",
    "sprache": "Deutsch",
    "schlagwörter": ["Klassiker", "Archäologie", "Wichtigsten", "Fundorte", "Ausgrabungsstätten"]
  },
  {
    "titel": "Der Mann aus dem Eis",
    "autor": "Angelika Fleckinger und Hubert Steiner",
    "sprache": "Deutsch",
    "schlagwörter": []
  },
  {
    "titel": "Die Geschichte der Gerichtsbarkeit: Vom Gottesurteil bis zum Beginn der modernen Rechtsprechung - 1000 Jahre Grausamkeit",
    "autor": "Wolfgang Schild",
    "sprache": "Deutsch",
    "schlagwörter": ["Geschichte", "Gerichtsbarkeit", "Gottesurteil", "Beginn", "Modernen", "Rechtsprechung"]
  },
  {
    "titel": "Folter, Pranger, Scheiterhaufen: Rechtsprechung im Mittelalter",
    "autor": "Wolfgang Schild",
    "sprache": "Deutsch",
    "schlagwörter": ["Folter", "Pranger", "Scheiterhaufen", "Rechtsprechung", "Mittelalter"]
  },
  {
    "titel": "Die Schweiz vor Christus",
    "autor": "Claudia Schnieper und Nicolas Faure",
    "sprache": "Deutsch",
    "schlagwörter": ["Schweiz", "Christus"]
  },
  {
    "titel": "Faszination Archäologie",
    "autor": "Paul G. Bahn",
    "sprache": "Deutsch",
    "schlagwörter": ["Faszination", "Archäologie"]
  },
  {
    "titel": "Ötzi: Der Mann aus dem Eis - Alles Wissenswerte zum Nachschlagen und Staunen",
    "autor": "Angelika Fleckinger",
    "sprache": "Deutsch",
    "schlagwörter": ["Wissenswerte", "Nachschlagen", "Staunen"]
  },
  {
    "titel": "Heavenly Bodies: Cult Treasures and Spectacular Saints from the Catacombs",
    "autor": "Thames and Hudson",
    "sprache": "Englisch",
    "schlagwörter": ["Heavenly", "Treasures", "Spectacular", "Saints", "Catacombs"]
  },
  {
    "titel": "Kaiserburg-Museum des Germanischen Nationalmuseums",
    "autor": "Germanisches Nationalmuseum",
    "sprache": "Deutsch",
    "schlagwörter": ["Museum", "Kaiserburg", "Germanischen", "Nationalmuseums"]
  },
  {
    "titel": "Gerichtsbarkeit im Elbe-Weser-Raum 1546-1670",
    "autor": "Jürgen Hoops von Scheeßel",
    "sprache": "Deutsch",
    "schlagwörter": ["Gerichtsbarkeit", "Weser-Raum"]
  },
  {
    "titel": "Rüstkammer Schloss Glatt",
    "autor": "G. H. Bidermann",
    "sprache": "Deutsch",
    "schlagwörter": ["Rüstkammer", "Schloss"]
  },
  {
    "titel": "The Most Complete Reference Book Ever Assembled: The Gun Digest Book of .22 Rimfire Rifles, Pistols & Ammunition",
    "autor": "James E. House",
    "sprache": "Englisch",
    "schlagwörter": ["Complete", "Reference", "Assembled", "Digest", "Rimfire", "Rifles"]
  },
  {
    "titel": "The Kings and Queens of England",
    "autor": "Orion Books",
    "sprache": "Englisch",
    "schlagwörter": ["Queens", "England"]
  },
  {
    "titel": "World War II Musées 1939-1945 Guide Europe",
    "autor": "Guide",
    "sprache": "Französisch",
    "schlagwörter": ["Weltkrieg", "Reiseführer", "Europe"]
  },
  {
    "titel": "Hinrichtungen und Leibstrafen",
    "autor": "Franz Schmidt",
    "sprache": "Deutsch",
    "schlagwörter": ["Hinrichtungen", "Leibstrafen"]
  },
  {
    "titel": "Das maurische Spanien: Geschichte und Kultur",
    "autor": "Georg Bossong",
    "sprache": "Deutsch",
    "schlagwörter": ["Maurische", "Spanien", "Geschichte", "Kultur"]
  },
  {
    "titel": "Warum du echt einmalig bist, Papa",
    "autor": "Alisa",
    "sprache": "Deutsch",
    "schlagwörter": ["Einmalig"]
  },
  {
    "titel": "Nürnberger Kriminalgeschichte: Henkerhaus, Lochgefängnis und Schuldturm",
    "autor": "Nürnberg Stadt",
    "sprache": "Deutsch",
    "schlagwörter": ["Nürnberger", "Kriminalgeschichte", "Henkerhaus", "Lochgefängnis", "Schuldturm"]
  },
  {
    "titel": "Das Lochgefängnis: Tortur und Richtung in Alt-Nürnberg",
    "autor": "Hermann Knapp",
    "sprache": "Deutsch",
    "schlagwörter": ["Lochgefängnis", "Tortur", "Richtung", "Nürnberg"]
  },
  {
    "titel": "The British Soldier 1914-1918",
    "autor": "Lawrence Brown",
    "sprache": "Englisch",
    "schlagwörter": ["British", "Soldier"]
  },
  {
    "titel": "The French Infantryman 1914-1918",
    "autor": "Yann Thomas",
    "sprache": "Englisch",
    "schlagwörter": ["French", "Infantryman"]
  },
  {
    "titel": "The Belgian Soldier 1914-1918",
    "autor": "Pierre Lierneux",
    "sprache": "Englisch",
    "schlagwörter": ["Belgian", "Soldier"]
  },
  {
    "titel": "The German Soldier 1914-1918",
    "autor": "Yann Thomas",
    "sprache": "Englisch",
    "schlagwörter": ["German", "Soldier"]
  },
  {
    "titel": "The American Soldier 1914-1918",
    "autor": "Dominique François",
    "sprache": "Englisch",
    "schlagwörter": ["American", "Soldier"]
  },
  {
    "titel": "Mortal Monarchs: 1000 Years of Royal Deaths",
    "autor": "Suzie Edge",
    "sprache": "Englisch",
    "schlagwörter": ["Mortal", "Monarchs", "Deaths"]
  },
  {
    "titel": "A Short History of the Mughal Empire",
    "autor": "Michael Fischer",
    "sprache": "Englisch",
    "schlagwörter": ["Mughal", "Geschichte", "History", "Empire"]
  },
  {
    "titel": "National Army Museum",
    "autor": "Souvenir Guide",
    "sprache": "Englisch",
    "schlagwörter": ["Reiseführer", "Museum", "National"]
  },
  {
    "titel": "Kalamkari Temple Hangings",
    "autor": "Anna L. Dallapiccola",
    "sprache": "Englisch",
    "schlagwörter": ["Tempel/Architektur", "Kalamkari", "Temple", "Hangings"]
  },
  {
    "titel": "The Great Mughals: Architecture and Opulence",
    "autor": "Susan Stronge",
    "sprache": "Englisch",
    "schlagwörter": ["Mughal", "Mughals", "Architecture", "Opulence"]
  }
]
